LICENSE
MANIFEST.in
README.rst
requirements.txt
setup.py
dcard/__init__.py
dcard/api.py
dcard/cli.py
dcard/dcard.py
dcard/forums.py
dcard/manager.py
dcard/posts.py
dcard/utils.py
dcard_spider.egg-info/PKG-INFO
dcard_spider.egg-info/SOURCES.txt
dcard_spider.egg-info/dependency_links.txt
dcard_spider.egg-info/entry_points.txt
dcard_spider.egg-info/not-zip-safe
dcard_spider.egg-info/requires.txt
dcard_spider.egg-info/top_level.txt